{
  "login": "emilroz",
  "id": 2600663,
  "node_id": "MDQ6VXNlcjI2MDA2NjM=",
  "avatar_url": "https://avatars2.githubusercontent.com/u/2600663?v=4",
  "gravatar_id": "",
  "url": "https://api.github.com/users/emilroz",
  "html_url": "https://github.com/emilroz",
  "followers_url": "https://api.github.com/users/emilroz/followers",
  "following_url": "https://api.github.com/users/emilroz/following{/other_user}",
  "gists_url": "https://api.github.com/users/emilroz/gists{/gist_id}",
  "starred_url": "https://api.github.com/users/emilroz/starred{/owner}{/repo}",
  "subscriptions_url": "https://api.github.com/users/emilroz/subscriptions",
  "organizations_url": "https://api.github.com/users/emilroz/orgs",
  "repos_url": "https://api.github.com/users/emilroz/repos",
  "events_url": "https://api.github.com/users/emilroz/events{/privacy}",
  "received_events_url": "https://api.github.com/users/emilroz/received_events",
  "type": "User",
  "site_admin": false,
  "name": "Emil Rozbicki",
  "company": "@glencoesoftware ",
  "blog": "www.glencoesoftware.com",
  "location": "Wrocław",
  "email": null,
  "hireable": null,
  "bio": null,
  "public_repos": 31,
  "public_gists": 11,
  "followers": 5,
  "following": 5,
  "created_at": "2012-10-19T15:47:54Z",
  "updated_at": "2018-06-08T10:52:15Z"
}
